LICENSE
README.md
pyproject.toml
setup.cfg
setup.py
anchio/__init__.py
anchio/api_client.py
anchio/api_response.py
anchio/configuration.py
anchio/exceptions.py
anchio/py.typed
anchio/rest.py
anchio/api/__init__.py
anchio/api/default_api.py
anchio/models/__init__.py
anchio/models/amount.py
anchio/models/anch_rest_api_utils_filters_contract_filter_schema_contractfilterschema_enum1.py
anchio/models/anch_rest_api_utils_filters_contract_filter_schema_contractfilterschema_enum2.py
anchio/models/anch_rest_api_utils_filters_employee_filter_schema_employeefilterschema_enum1.py
anchio/models/anch_rest_api_utils_filters_employee_filter_schema_employeefilterschema_enum2.py
anchio/models/anch_rest_api_utils_filters_tool_access_filter_schema_toolaccessfilterschema_enum1.py
anchio/models/anch_rest_api_utils_filters_tool_access_filter_schema_toolaccessfilterschema_enum2.py
anchio/models/api_key_context_input.py
anchio/models/api_key_context_output.py
anchio/models/api_key_provider.py
anchio/models/api_key_schema.py
anchio/models/api_key_schema_input.py
anchio/models/api_key_schema_output.py
anchio/models/bank_account_provider.py
anchio/models/bank_account_schema.py
anchio/models/change_password.py
anchio/models/checkout_session_request_schema.py
anchio/models/checkout_session_schema.py
anchio/models/company_role_schema.py
anchio/models/company_schema.py
anchio/models/company_schema_input.py
anchio/models/company_schema_output.py
anchio/models/company_sync_status.py
anchio/models/content_type_natural_key.py
anchio/models/contract_amount.py
anchio/models/contract_amount1.py
anchio/models/contract_schema.py
anchio/models/create_api_key_schema.py
anchio/models/default_schema.py
anchio/models/department_schema.py
anchio/models/employee_role_schema.py
anchio/models/employee_role_tool_schema.py
anchio/models/employee_schema.py
anchio/models/employee_schema_input.py
anchio/models/employee_schema_output.py
anchio/models/employee_tool_access_request_schema.py
python_anchio.egg-info/PKG-INFO
python_anchio.egg-info/SOURCES.txt
python_anchio.egg-info/dependency_links.txt
python_anchio.egg-info/requires.txt
python_anchio.egg-info/top_level.txt
