Metadata-Version: 2.1
Name: python-anchio
Version: 0.1.9
Summary: Anch.io
Home-page: https://github.com/Anch-io/python-anchio
Author: Anch.io
Author-email: opensource@anchio.app
License: UNKNOWN
Keywords: OpenAPI,OpenAPI-Generator,Anch.io
Platform: UNKNOWN
License-File: LICENSE
